pyhomepilot/__init__.py
pyhomepilot/api.py
pyhomepilot/auth.py
pyhomepilot/const.py
pyhomepilot/utils.py
pyhomepilot/devices/__init__.py
pyhomepilot/devices/actuator.py
pyhomepilot/devices/blind.py
pyhomepilot/devices/device.py
pyhomepilot-0.0.3.dist-info/LICENSE
pyhomepilot-0.0.3.dist-info/METADATA
pyhomepilot-0.0.3.dist-info/WHEEL
pyhomepilot-0.0.3.dist-info/top_level.txt
pyhomepilot-0.0.3.dist-info/RECORD
