Metadata-Version: 2.1
Name: pyhomepilot
Version: 0.0.3
Summary: Unofficial Rademacher HomePilot API wrapper
Home-page: https://github.com/nico0302/pyhomepilot
Author: Nicolas Gres
Author-email: nicolas@gres.io
License: MIT
Platform: UNKNOWN
Classifier: Programming Language :: Python :: 3
Classifier: License :: OSI Approved :: MIT License
Classifier: Operating System :: OS Independent
Requires-Python: >=3.6
License-File: LICENSE
Requires-Dist: aiohttp
